django_rungevent
