Metadata-Version: 1.0
Name: django-rungevent
Version: 0.3.3
Summary: Django Gevent Run Command
Home-page: https://github.com/tr4n2uil/django-rungevent
Author: Vibhaj Rajan
Author-email: vibhaj8@gmail.com
License: MIT
Keywords: django gevent
Platform: UNKNOWN
